.gitignore
LICENSE
README.md
pyproject.toml
setup.cfg
setup.py
ephemere/__init__.py
ephemere/archive.py
ephemere/constants.py
ephemere/rmplanets.py
ephemere.egg-info/PKG-INFO
ephemere.egg-info/SOURCES.txt
ephemere.egg-info/dependency_links.txt
ephemere.egg-info/not-zip-safe
ephemere.egg-info/requires.txt
ephemere.egg-info/top_level.txt
extras/example.py
tests/test_archive.py
tests/test_rmplanets.py