Metadata-Version: 2.1
Name: ephemere
Version: 0.1.0
Summary: Get exoplanet orbit predictions
Home-page: https://github.com/vandalt/ephemere
Author: Thomas Vandal
Author-email: thomasvandal@hotmail.com
License: MIT License
Platform: UNKNOWN
Provides-Extra: dev
License-File: LICENSE
